apoo/__init__.py
apoo/apoo.py
apoo-0.1.0.dist-info/METADATA
apoo-0.1.0.dist-info/WHEEL
apoo-0.1.0.dist-info/RECORD
