Metadata-Version: 2.1
Name: apoo
Version: 0.1.0
Summary: Automatic Prompt Optimizer
Author: Teïlo M
Author-email: teilomillet@gmail.com
Requires-Python: >=3.11,<4.0
Classifier: Programming Language :: Python :: 3
Classifier: Programming Language :: Python :: 3.11
Classifier: Programming Language :: Python :: 3.12
